qurane/__init__.py
qurane/quran.py
qurane/search.py
qurane/tafser.py
qurane-1.0.dist-info/METADATA
qurane-1.0.dist-info/WHEEL
qurane-1.0.dist-info/top_level.txt
qurane-1.0.dist-info/RECORD
