Metadata-Version: 2.1
Name: qurane
Version: 1.0
Summary: A modern and advanced Quran library for Arabic text and Tafsir
Home-page: 
Author: Khattab_Aluqba
Author-email: exmidleg@gmail.com
License: MIT
Classifier: Programming Language :: Python :: 3
Classifier: License :: OSI Approved :: MIT License
Classifier: Operating System :: OS Independent
Requires-Python: >=3.6
